ttvfaster/__init__.py
ttvfaster/_ttvfaster.cpython-38-darwin.so
ttvfaster/ttvfaster.py
ttvfaster-0.1.0.dist-info/LICENSE
ttvfaster-0.1.0.dist-info/METADATA
ttvfaster-0.1.0.dist-info/WHEEL
ttvfaster-0.1.0.dist-info/top_level.txt
ttvfaster-0.1.0.dist-info/RECORD
